schemaplus_shopify_utils/__init__.py
schemaplus_shopify_utils/product_utils.py
schemaplus_shopify_utils-0.1.1.dist-info/licenses/LICENSE
schemaplus_shopify_utils-0.1.1.dist-info/METADATA
schemaplus_shopify_utils-0.1.1.dist-info/WHEEL
schemaplus_shopify_utils-0.1.1.dist-info/top_level.txt
schemaplus_shopify_utils-0.1.1.dist-info/RECORD
