Metadata-Version: 2.4
Name: schemaplus-shopify-utils
Version: 0.1.1
Summary: Utility functions for working with the Shopify API
Home-page: https://github.com/uppercasebrands-private/schemaplus-shopify-utils
Author: SchemaPlus
Author-email: SchemaPlus <support@schemaplus.io>
License: MIT
Project-URL: Homepage, https://github.com/uppercasebrands-private/schemaplus-shopify-utils
Project-URL: Bug Tracker, https://github.com/uppercasebrands-private/schemaplus-shopify-utils/issues
Classifier: Programming Language :: Python :: 3
Classifier: License :: OSI Approved :: MIT License
Classifier: Operating System :: OS Independent
Requires-Python: >=3.6
License-File: LICENSE
Requires-Dist: requests>=2.25.0
Dynamic: author
Dynamic: home-page
Dynamic: license-file
Dynamic: requires-python
